mcp_pyodbc_server/__init__.py
mcp_pyodbc_server/server.py
mseep_mcp_pyodbc_server-0.5.1.dist-info/licenses/LICENSE
mseep_mcp_pyodbc_server-0.5.1.dist-info/METADATA
mseep_mcp_pyodbc_server-0.5.1.dist-info/WHEEL
mseep_mcp_pyodbc_server-0.5.1.dist-info/entry_points.txt
mseep_mcp_pyodbc_server-0.5.1.dist-info/top_level.txt
mseep_mcp_pyodbc_server-0.5.1.dist-info/RECORD
