Metadata-Version: 2.4
Name: mseep-mcp-pyodbc-server
Version: 0.5.1
Summary: A simple MCP ODBC server using FastAPI and PyODBC
Author-email: mseep <support@skydeck.ai>
Requires-Python: >=3.10
License-File: LICENSE
Requires-Dist: mcp[cli]>=1.4.1
Requires-Dist: pyodbc>=5.2.0
Requires-Dist: python-dotenv>=1.0.1
Dynamic: license-file
